mlop/__init__.py
mlop/__main__.py
mlop/api.py
mlop/auth.py
mlop/compat/__init__.py
mlop/compat/lightning.py
mlop/compat/torch.py
mlop/compat/transformers.py
mlop/data.py
mlop/file.py
mlop/iface.py
mlop/init.py
mlop/log.py
mlop/op.py
mlop/sets.py
mlop/store.py
mlop/sys.py
mlop/util.py
trainy_mlop-0.0.2.dev20251212091703.dist-info/LICENSE
trainy_mlop-0.0.2.dev20251212091703.dist-info/METADATA
trainy_mlop-0.0.2.dev20251212091703.dist-info/WHEEL
trainy_mlop-0.0.2.dev20251212091703.dist-info/entry_points.txt
trainy_mlop-0.0.2.dev20251212091703.dist-info/RECORD
