Metadata-Version: 2.3
Name: trainy-mlop
Version: 0.0.2.dev20251212091703
Summary: Trainy MLOp
Author: jqssun
Requires-Python: >=3.9,<4.0
Classifier: Programming Language :: Python :: 3
Classifier: Programming Language :: Python :: 3.9
Classifier: Programming Language :: Python :: 3.10
Classifier: Programming Language :: Python :: 3.11
Classifier: Programming Language :: Python :: 3.12
Classifier: Programming Language :: Python :: 3.13
Provides-Extra: full
Requires-Dist: GitPython (>=3.1)
Requires-Dist: httpx[http2] (>=0.24)
Requires-Dist: keyring (>=24.0)
Requires-Dist: keyrings-alt (>=5.0)
Requires-Dist: pillow (>=10.0)
Requires-Dist: psutil (>=5.9)
Requires-Dist: pynvml (>=11.5) ; extra == "full"
Requires-Dist: rich (>=13.0)
Requires-Dist: soundfile (>=0.12)
